{
  "main": {
    "id": "e2e78060ad4ae630",
    "type": "split",
    "children": [
      {
        "id": "18804aad998a6db8",
        "type": "tabs",
        "children": [
          {
            "id": "069b9c3f2723af9d",
            "type": "leaf",
            "state": {
              "type": "markdown",
              "state": {
                "file": "14ab 英语单词词频排序coca20000和coca60000.md",
                "mode": "source",
                "source": false
              }
            }
          }
        ]
      },
      {
        "id": "152834ba7e32bf30",
        "type": "tabs",
        "children": [
          {
            "id": "d6b07f5fd03cbb61",
            "type": "leaf",
            "state": {
              "type": "markdown",
              "state": {
                "file": "14ab 英语单词词频排序coca20000和coca60000.md",
                "mode": "source",
                "source": false
              }
            }
          }
        ]
      },
      {
        "id": "a24d0748a6ed58ef",
        "type": "tabs",
        "children": [
          {
            "id": "0e05c391533a852c",
            "type": "leaf",
            "state": {
              "type": "markdown",
              "state": {
                "file": "14ab 英语单词词频排序coca20000和coca60000.md",
                "mode": "source",
                "source": false
              }
            }
          }
        ]
      },
      {
        "id": "c02cd7f24ecd343e",
        "type": "tabs",
        "children": [
          {
            "id": "7bf9b2184406cb7e",
            "type": "leaf",
            "state": {
              "type": "markdown",
              "state": {
                "file": "14ab 英语单词词频排序coca20000和coca60000.md",
                "mode": "source",
                "source": false
              }
            }
          }
        ]
      },
      {
        "id": "86be11e32d0ca0eb",
        "type": "tabs",
        "children": [
          {
            "id": "32ba1fc66ccf861e",
            "type": "leaf",
            "state": {
              "type": "markdown",
              "state": {
                "file": "14ab 英语单词词频排序coca20000和coca60000.md",
                "mode": "source",
                "source": false
              }
            }
          }
        ]
      },
      {
        "id": "64d1cf76bec47325",
        "type": "tabs",
        "children": [
          {
            "id": "f626093f9d4f4e9b",
            "type": "leaf",
            "state": {
              "type": "markdown",
              "state": {
                "file": "14ab 英语单词词频排序coca20000和coca60000.md",
                "mode": "source",
                "source": false
              }
            }
          }
        ]
      },
      {
        "id": "09e9f1708d1cf749",
        "type": "tabs",
        "children": [
          {
            "id": "d00852ae5655e72e",
            "type": "leaf",
            "state": {
              "type": "markdown",
              "state": {
                "file": "15 色情电影.md",
                "mode": "preview",
                "source": false
              }
            }
          }
        ]
      }
    ],
    "direction": "vertical"
  },
  "left": {
    "id": "e4e7d2deb33d306a",
    "type": "mobile-drawer",
    "children": [
      {
        "id": "9d8de04e87b485a9",
        "type": "leaf",
        "state": {
          "type": "file-explorer",
          "state": {
            "sortOrder": "alphabetical"
          }
        }
      },
      {
        "id": "cc7d2f4279175618",
        "type": "leaf",
        "state": {
          "type": "search",
          "state": {
            "query": "",
            "matchingCase": false,
            "explainSearch": false,
            "collapseAll": false,
            "extraContext": false,
            "sortOrder": "alphabetical"
          }
        }
      },
      {
        "id": "d2a04a028b96235b",
        "type": "leaf",
        "state": {
          "type": "tag",
          "state": {
            "sortOrder": "frequency",
            "useHierarchy": true
          }
        }
      },
      {
        "id": "550e79f53af907cb",
        "type": "leaf",
        "state": {
          "type": "starred",
          "state": {}
        }
      }
    ],
    "currentTab": 0
  },
  "right": {
    "id": "c642a82eb8da5f28",
    "type": "mobile-drawer",
    "children": [
      {
        "id": "ad5bddcf98d846b8",
        "type": "leaf",
        "state": {
          "type": "calendar",
          "state": {}
        }
      },
      {
        "id": "7acf6f7282195c18",
        "type": "leaf",
        "state": {
          "type": "backlink",
          "state": {
            "file": "15 色情电影.md",
            "collapseAll": false,
            "extraContext": true,
            "sortOrder": "byModifiedTime",
            "showSearch": false,
            "searchQuery": "",
            "backlinkCollapsed": false,
            "unlinkedCollapsed": true
          }
        }
      },
      {
        "id": "ebc6151153e24950",
        "type": "leaf",
        "state": {
          "type": "outgoing-link",
          "state": {
            "file": "15 色情电影.md",
            "linksCollapsed": false,
            "unlinkedCollapsed": true
          }
        }
      },
      {
        "id": "de2174e1556a5663",
        "type": "leaf",
        "state": {
          "type": "outline",
          "state": {
            "file": "15 色情电影.md"
          }
        }
      },
      {
        "id": "a2e7267e7bdbc7ea",
        "type": "leaf",
        "state": {
          "type": "review-queue-list-view",
          "state": {}
        }
      }
    ],
    "currentTab": 0
  },
  "active": "d00852ae5655e72e",
  "lastOpenFiles": [
    "14ab 英语单词词频排序coca20000和coca60000.md"
  ]
}