{
  "main": {
    "id": "97cfcbb0e7ebda1c",
    "type": "split",
    "children": [
      {
        "id": "fef5a996e78c5c37",
        "type": "tabs",
        "children": [
          {
            "id": "8f658a7ce713608e",
            "type": "leaf",
            "state": {
              "type": "markdown",
              "state": {
                "file": "3a 学习 obsidian.md",
                "mode": "source",
                "source": false
              }
            }
          },
          {
            "id": "36247cb0ea75c36e",
            "type": "leaf",
            "state": {
              "type": "markdown",
              "state": {
                "file": "z_文献笔记/20.10 所长林超：给年轻人的跨学科通识课.md",
                "mode": "source",
                "source": false
              }
            }
          }
        ],
        "currentTab": 1
      }
    ],
    "direction": "vertical"
  },
  "left": {
    "id": "1e7b9af277459a22",
    "type": "split",
    "children": [
      {
        "id": "228a346f9f03c79c",
        "type": "tabs",
        "children": [
          {
            "id": "68661d0d558015ea",
            "type": "leaf",
            "state": {
              "type": "file-explorer",
              "state": {
                "sortOrder": "alphabetical"
              }
            }
          },
          {
            "id": "4873f8c1a5b4841b",
            "type": "leaf",
            "state": {
              "type": "search",
              "state": {
                "query": "王阳明",
                "matchingCase": false,
                "explainSearch": false,
                "collapseAll": false,
                "extraContext": false,
                "sortOrder": "alphabetical"
              }
            }
          },
          {
            "id": "a679fcef86838788",
            "type": "leaf",
            "state": {
              "type": "starred",
              "state": {}
            }
          }
        ]
      }
    ],
    "direction": "horizontal",
    "width": 354.5
  },
  "right": {
    "id": "d6f196d28275fe53",
    "type": "split",
    "children": [
      {
        "id": "105320350c55fd93",
        "type": "tabs",
        "children": [
          {
            "id": "8ee9a25e562d37ff",
            "type": "leaf",
            "state": {
              "type": "backlink",
              "state": {
                "file": "z_文献笔记/20.10 所长林超：给年轻人的跨学科通识课.md",
                "collapseAll": false,
                "extraContext": true,
                "sortOrder": "byModifiedTime",
                "showSearch": false,
                "searchQuery": "",
                "backlinkCollapsed": false,
                "unlinkedCollapsed": true
              }
            }
          },
          {
            "id": "a4dd6ba33a1c7490",
            "type": "leaf",
            "state": {
              "type": "outgoing-link",
              "state": {
                "file": "z_文献笔记/20.10 所长林超：给年轻人的跨学科通识课.md",
                "linksCollapsed": false,
                "unlinkedCollapsed": true
              }
            }
          },
          {
            "id": "6e1971dfdbe51322",
            "type": "leaf",
            "state": {
              "type": "tag",
              "state": {
                "sortOrder": "frequency",
                "useHierarchy": true
              }
            }
          },
          {
            "id": "a7cc7d0085d3440a",
            "type": "leaf",
            "state": {
              "type": "outline",
              "state": {
                "file": "z_文献笔记/20.10 所长林超：给年轻人的跨学科通识课.md"
              }
            }
          },
          {
            "id": "90fb7c711483221e",
            "type": "leaf",
            "state": {
              "type": "review-queue-list-view",
              "state": {}
            }
          },
          {
            "id": "d5f360bf2a05f151",
            "type": "leaf",
            "state": {
              "type": "timeline",
              "state": {}
            }
          },
          {
            "id": "f8520cfef09891eb",
            "type": "leaf",
            "state": {
              "type": "advanced-tables-toolbar",
              "state": {}
            }
          },
          {
            "id": "d74ea903648a4f34",
            "type": "leaf",
            "state": {
              "type": "calendar",
              "state": {}
            }
          }
        ]
      }
    ],
    "direction": "horizontal",
    "width": 300,
    "collapsed": true
  },
  "left-ribbon": {
    "hiddenItems": {
      "obsidian42-brat:BRAT": false,
      "meld-encrypt:Create new encrypted note": false,
      "switcher:Open quick switcher": false,
      "graph:Open graph view": false,
      "canvas:Create new canvas": false,
      "daily-notes:Open today's daily note": false,
      "templates:Insert template": false,
      "command-palette:Open command palette": false,
      "zk-prefixer:Create new unique note": false,
      "obsidian-spaced-repetition:Review flashcards": false,
      "table-editor-obsidian:Advanced Tables Toolbar": false,
      "periodic-notes:Open today": false
    }
  },
  "active": "36247cb0ea75c36e",
  "lastOpenFiles": [
    "24 演讲.md",
    "_coverpage.md",
    "_navbar.md",
    "3d 我们的大中国.md",
    "3cd 广东话.md",
    "z_文献笔记/20.6a The Tim Ferriss Show.md",
    "z_daily/2023-01-06-Fri-w01.md",
    "work/0 README.md",
    "work/weekly/2022 W46.md",
    "work/weekly/2022 W47.md"
  ]
}